setup.py
ppp_datamodel/__init__.py
ppp_datamodel/exceptions.py
ppp_datamodel/log.py
ppp_datamodel.egg-info/PKG-INFO
ppp_datamodel.egg-info/SOURCES.txt
ppp_datamodel.egg-info/dependency_links.txt
ppp_datamodel.egg-info/top_level.txt
ppp_datamodel/communication/__init__.py
ppp_datamodel/communication/request.py
ppp_datamodel/communication/response.py
ppp_datamodel/communication/traceitem.py
ppp_datamodel/nodes/__init__.py
ppp_datamodel/nodes/abstractnode.py
ppp_datamodel/nodes/list.py
ppp_datamodel/nodes/list_operators.py
ppp_datamodel/nodes/missing.py
ppp_datamodel/nodes/resource.py
ppp_datamodel/nodes/sentence.py
ppp_datamodel/nodes/triple.py
ppp_datamodel/utils/__init__.py
ppp_datamodel/utils/attributesholder.py
ppp_datamodel/utils/serializableattributesholder.py
ppp_datamodel/utils/tests.py
ppp_datamodel/utils/typedattributesholder.py