Metadata-Version: 1.1
Name: ppp-datamodel
Version: 0.6.11
Summary: Data model for the Projet Pensées Profondes.
Home-page: https://github.com/ProjetPP/PPP-datamodel-Python
Author: Valentin Lorentz
Author-email: valentin.lorentz+ppp@ens-lyon.org
License: MIT
Platform: UNKNOWN
Classifier: Development Status :: 1 - Planning
Classifier: Intended Audience :: Developers
Classifier: License :: OSI Approved :: MIT License
Classifier: Operating System :: OS Independent
Classifier: Programming Language :: Python :: 3
Classifier: Programming Language :: Python :: 3.2
Classifier: Programming Language :: Python :: 3.3
Classifier: Programming Language :: Python :: 3.4
Classifier: Topic :: Software Development :: Libraries
